awslabs/__init__.py
awslabs/github_actions_mcp_server/__init__.py
awslabs/github_actions_mcp_server/main.py
awslabs_github_actions_mcp_server-0.1.2.dist-info/licenses/LICENSE
awslabs_github_actions_mcp_server-0.1.2.dist-info/METADATA
awslabs_github_actions_mcp_server-0.1.2.dist-info/WHEEL
awslabs_github_actions_mcp_server-0.1.2.dist-info/entry_points.txt
awslabs_github_actions_mcp_server-0.1.2.dist-info/top_level.txt
awslabs_github_actions_mcp_server-0.1.2.dist-info/RECORD
